CHANGES.txt
README.txt
ez_setup.py
setup.py
src/sourcecodegen/__init__.py
src/sourcecodegen/generation.py
src/sourcecodegen/visitor.py
src/sourcecodegen.egg-info/PKG-INFO
src/sourcecodegen.egg-info/SOURCES.txt
src/sourcecodegen.egg-info/dependency_links.txt
src/sourcecodegen.egg-info/not-zip-safe
src/sourcecodegen.egg-info/top_level.txt
src/sourcecodegen/tests/__init__.py
src/sourcecodegen/tests/base.py
src/sourcecodegen/tests/py24.py
src/sourcecodegen/tests/py25plus.py