Metadata-Version: 1.0
Name: sourcecodegen
Version: 0.6.9
Summary: A Python source-code generator based on the ``compiler.ast`` abstract syntax tree.
Home-page: UNKNOWN
Author: Malthe Borch
Author-email: mborch@gmail.com
License: BSD
Keywords: python source-code generation ast
Platform: UNKNOWN
Classifier: Development Status :: 3 - Alpha
Classifier: Intended Audience :: Developers
Classifier: Programming Language :: Python
Classifier: Topic :: Internet :: WWW/HTTP
Classifier: Topic :: Internet :: WWW/HTTP :: Dynamic Content
Classifier: Topic :: Internet :: WWW/HTTP :: WSGI
